fluidattacks_timedoctor_sdk/__init__.py
fluidattacks_timedoctor_sdk/_logger.py
fluidattacks_timedoctor_sdk/core.py
fluidattacks_timedoctor_sdk/py.typed
fluidattacks_timedoctor_sdk/auth/__init__.py
fluidattacks_timedoctor_sdk/auth/_core.py
fluidattacks_timedoctor_sdk/auth/_new_token.py
fluidattacks_timedoctor_sdk/auth/_revoke.py
fluidattacks_timedoctor_sdk/client/__init__.py
fluidattacks_timedoctor_sdk/client/_common.py
fluidattacks_timedoctor_sdk/client/_get_companies.py
fluidattacks_timedoctor_sdk/client/_get_projects.py
fluidattacks_timedoctor_sdk/client/_get_users.py
fluidattacks_timedoctor_sdk/client/_computer_activity/__init__.py
fluidattacks_timedoctor_sdk/client/_computer_activity/_decode.py
fluidattacks_timedoctor_sdk/client/_computer_activity/_get.py
fluidattacks_timedoctor_sdk/client/_worklog/__init__.py
fluidattacks_timedoctor_sdk/client/_worklog/_decode.py
fluidattacks_timedoctor_sdk/client/_worklog/_get.py
fluidattacks_timedoctor_sdk-2.1.0.dist-info/WHEEL
fluidattacks_timedoctor_sdk-2.1.0.dist-info/METADATA
fluidattacks_timedoctor_sdk-2.1.0.dist-info/RECORD
